snakemake_storage_plugin_git/__init__.py
snakemake_storage_plugin_git-0.1.0.dist-info/METADATA
snakemake_storage_plugin_git-0.1.0.dist-info/WHEEL
snakemake_storage_plugin_git-0.1.0.dist-info/licenses/LICENSE
snakemake_storage_plugin_git-0.1.0.dist-info/RECORD
